[
  {
    "obt_number": "580033347514",
    "recipient_name": "新店裕隆城 studio A",
    "cod_amount": "0",
    "created_at": "2026/05/08",
    "status": "順利送達",
    "order_id": "",
    "notes": "",
    "sender_name": "STUDIO A板橋誠品"
  },
  {
    "obt_number": "580033349972",
    "recipient_name": "STUDIO A 新店裕隆城",
    "cod_amount": "0",
    "created_at": "2026/05/08",
    "status": "順利送達",
    "order_id": "門市",
    "notes": "068260508001,MH5N4TA/A",
    "sender_name": "晶實中壢大江"
  },
  {
    "obt_number": "580033354411",
    "recipient_name": "Studio A 新店裕隆城",
    "cod_amount": "0",
    "created_at": "2026/05/09",
    "status": "順利送達",
    "order_id": "",
    "notes": "",
    "sender_name": "晶實科技台南西門"
  },
  {
    "obt_number": "580033356696",
    "recipient_name": "Studio A-新店裕隆城",
    "cod_amount": "0",
    "created_at": "2026/05/12",
    "status": "順利送達",
    "order_id": "",
    "notes": "",
    "sender_name": "Studio A 三多門市"
  },
  {
    "obt_number": "580033357192",
    "recipient_name": "STUDIO A 新店裕隆城",
    "cod_amount": "0",
    "created_at": "2026/05/11",
    "status": "順利送達",
    "order_id": "門市",
    "notes": "068260510004,MEU44TA/A",
    "sender_name": "晶實中壢大江"
  },
  {
    "obt_number": "580033362904",
    "recipient_name": "STUDIO A新店裕隆城",
    "cod_amount": "0",
    "created_at": "2026/05/12",
    "status": "順利送達",
    "order_id": "門市調撥",
    "notes": "",
    "sender_name": "STUDIO A 夢時代門市"
  },
  {
    "obt_number": "580033377315",
    "recipient_name": "STUDIO A新店裕隆城",
    "cod_amount": "0",
    "created_at": "2026/05/13",
    "status": "順利送達",
    "order_id": "",
    "notes": "精密儀器﹑小心輕放!",
    "sender_name": "STUDIOA-苗栗尚順"
  },
  {
    "obt_number": "580033377521",
    "recipient_name": "新店裕隆城Studio A",
    "cod_amount": "0",
    "created_at": "2026/05/13",
    "status": "順利送達",
    "order_id": "",
    "notes": "高庫齡調撥",
    "sender_name": "STUDIO A 桃園統領"
  },
  {
    "obt_number": "580033391232",
    "recipient_name": "裕隆城STUDIOA",
    "cod_amount": "0",
    "created_at": "2026/05/15",
    "status": "順利送達",
    "order_id": "",
    "notes": "demo",
    "sender_name": "新西門STUDIO A"
  },
  {
    "obt_number": "580033399281",
    "recipient_name": "新店裕隆城",
    "cod_amount": "0",
    "created_at": "2026/05/16",
    "status": "順利送達",
    "order_id": "門市調撥",
    "notes": "068260515001",
    "sender_name": "STUDIO A 新竹光復"
  },
  {
    "obt_number": "580033413616",
    "recipient_name": "新店裕隆城",
    "cod_amount": "0",
    "created_at": "2026/05/19",
    "status": "順利送達",
    "order_id": "門市調撥",
    "notes": "068260518001",
    "sender_name": "STUDIO A 新竹光復"
  },
  {
    "obt_number": "907689908081",
    "recipient_name": "伍紳豪",
    "cod_amount": "0",
    "created_at": "2026/05/19",
    "status": "順利送達",
    "order_id": "001",
    "notes": "",
    "sender_name": "STUDIO A新店裕隆城"
  },
  {
    "obt_number": "909524092176",
    "recipient_name": "駱怡洳",
    "cod_amount": "0",
    "created_at": "2026/05/13",
    "status": "順利送達",
    "order_id": "客訂",
    "notes": "BG44437120",
    "sender_name": "晶實科技股份有限公司"
  },
  {
    "obt_number": "909524381282",
    "recipient_name": "張嘉峻",
    "cod_amount": "0",
    "created_at": "2026/05/12",
    "status": "順利送達",
    "order_id": "門市寄客",
    "notes": "購證號碼:BG44437212",
    "sender_name": "晶實科技股份有限公司"
  },
  {
    "obt_number": "909524433381",
    "recipient_name": "蔡瑞錩",
    "cod_amount": "0",
    "created_at": "2026/05/12",
    "status": "順利送達",
    "order_id": "",
    "notes": "BOSE SoundLink Max 藍牙揚聲器 黑色",
    "sender_name": "晶實科技股份有限公司"
  },
  {
    "obt_number": "909524690421",
    "recipient_name": "李幼珍 (江新公司)",
    "cod_amount": "0",
    "created_at": "2026/05/13",
    "status": "順利送達",
    "order_id": "寄客",
    "notes": "",
    "sender_name": "晶實科技股份有限公司"
  },
  {
    "obt_number": "909524781275",
    "recipient_name": "廖美鈺",
    "cod_amount": "0",
    "created_at": "2026/05/13",
    "status": "順利送達",
    "order_id": "寄客",
    "notes": "BG44437296",
    "sender_name": "晶實科技股份有限公司"
  },
  {
    "obt_number": "909524940441",
    "recipient_name": "謝政峰",
    "cod_amount": "0",
    "created_at": "2026/05/14",
    "status": "順利送達",
    "order_id": "",
    "notes": "studio A 裕隆城輔銷物",
    "sender_name": "晶實科技股份有限公司"
  },
  {
    "obt_number": "909525165531",
    "recipient_name": "林隆昌",
    "cod_amount": "0",
    "created_at": "2026/05/18",
    "status": "順利送達",
    "order_id": "客訂",
    "notes": "BG44437385",
    "sender_name": "晶實科技股份有限公司"
  },
  {
    "obt_number": "909525386843",
    "recipient_name": "STUDIO A士林維修中心",
    "cod_amount": "0",
    "created_at": "2026/05/16",
    "status": "順利送達",
    "order_id": "RMA",
    "notes": "",
    "sender_name": "晶實科技股份有限公司"
  },
  {
    "obt_number": "909525402984",
    "recipient_name": "STUDIO A士林維修中心",
    "cod_amount": "0",
    "created_at": "2026/05/16",
    "status": "順利送達",
    "order_id": "",
    "notes": "RMA",
    "sender_name": "晶實科技股份有限公司"
  },
  {
    "obt_number": "909525765054",
    "recipient_name": "廖竹語",
    "cod_amount": "0",
    "created_at": "2026/05/19",
    "status": "順利送達",
    "order_id": "",
    "notes": "",
    "sender_name": "晶實科技股份有限公司"
  },
  {
    "obt_number": "580033349452",
    "order_id": "062260508001",
    "recipient_name": "STUDIO A台中豐原",
    "sender_name": "晶實科技股份有限公司",
    "created_at": "2026/05/08",
    "notes": "MFHP4TA/A、50900172*3",
    "status": "順利送達",
    "queried_at": "2026-05-21T01:10:30"
  },
  {
    "obt_number": "580033354470",
    "order_id": "DOA",
    "recipient_name": "薇恩企業社",
    "sender_name": "晶實科技股份有限公司",
    "created_at": "2026/05/08",
    "notes": "068260506002",
    "status": "順利送達",
    "queried_at": "2026-05-21T01:10:30"
  },
  {
    "obt_number": "580033354481",
    "order_id": "DOA",
    "recipient_name": "尚宏電子股份有限公司",
    "sender_name": "晶實科技股份有限公司",
    "created_at": "2026/05/08",
    "notes": "068260506004",
    "status": "順利送達",
    "queried_at": "2026-05-21T01:10:31"
  },
  {
    "obt_number": "580033354815",
    "order_id": "055260508008",
    "recipient_name": "STUDIO A花蓮",
    "sender_name": "晶實科技股份有限公司",
    "created_at": "2026/05/08",
    "notes": "MF1H4TA/A",
    "status": "順利送達",
    "queried_at": "2026-05-21T01:10:32"
  },
  {
    "obt_number": "580033354826",
    "order_id": "012260508001",
    "recipient_name": "STUDIO A大億西門",
    "sender_name": "晶實科技股份有限公司",
    "created_at": "2026/05/08",
    "notes": "RMB13SV-DG、MFHP4TA/A",
    "status": "順利送達",
    "queried_at": "2026-05-21T01:10:32"
  },
  {
    "obt_number": "580033355232",
    "order_id": "調撥",
    "recipient_name": "STUDIO A台中中科",
    "sender_name": "晶實科技股份有限公司",
    "created_at": "2026/05/09",
    "notes": "",
    "status": "順利送達",
    "queried_at": "2026-05-21T01:10:29"
  },
  {
    "obt_number": "580033356064",
    "order_id": "門市調撥",
    "recipient_name": "STUDIO A新竹中正",
    "sender_name": "晶實科技股份有限公司",
    "created_at": "2026/05/10",
    "notes": "048260510001",
    "status": "順利送達",
    "queried_at": "2026-05-21T01:10:27"
  },
  {
    "obt_number": "580033356356",
    "order_id": "門市調撥",
    "recipient_name": "STUDIO A高雄三多",
    "sender_name": "晶實科技股份有限公司",
    "created_at": "2026/05/10",
    "notes": "044260510002",
    "status": "順利送達",
    "queried_at": "2026-05-21T01:10:28"
  },
  {
    "obt_number": "580033356674",
    "order_id": "門市寄客",
    "recipient_name": "STUDIO A岡山秀泰",
    "sender_name": "晶實科技股份有限公司",
    "created_at": "2026/05/10",
    "notes": "067260510002",
    "status": "順利送達",
    "queried_at": "2026-05-21T01:10:28"
  },
  {
    "obt_number": "909524098412",
    "order_id": "門市調撥",
    "recipient_name": "STUDIO A岡山秀泰",
    "sender_name": "晶實科技股份有限公司",
    "created_at": "2026/05/10",
    "notes": "067260510002",
    "status": "查無紀錄",
    "queried_at": "2026-05-21T01:20:03"
  },
  {
    "obt_number": "580033365053",
    "order_id": "",
    "recipient_name": "STUDIO A台中麗寶",
    "sender_name": "晶實科技股份有限公司",
    "created_at": "2026/05/11",
    "notes": "066260511001",
    "status": "順利送達",
    "queried_at": "2026-05-21T01:10:27"
  },
  {
    "obt_number": "580033376101",
    "order_id": "門市調撥",
    "recipient_name": "Straight A 輔大",
    "sender_name": "晶實科技股份有限公司",
    "created_at": "2026/05/12",
    "notes": "099260512036",
    "status": "順利送達",
    "queried_at": "2026-05-21T01:10:26"
  },
  {
    "obt_number": "580033382820",
    "order_id": "",
    "recipient_name": "STUDIO A羅東",
    "sender_name": "晶實科技股份有限公司",
    "created_at": "2026/05/13",
    "notes": "",
    "status": "順利送達",
    "queried_at": "2026-05-21T01:10:26"
  },
  {
    "obt_number": "580033385946",
    "order_id": "",
    "recipient_name": "STUDIO A桃園統領",
    "sender_name": "晶實科技股份有限公司",
    "created_at": "2026/05/13",
    "notes": "061260513003",
    "status": "順利送達",
    "queried_at": "2026-05-21T01:10:26"
  },
  {
    "obt_number": "580033388205",
    "order_id": "門市調撥",
    "recipient_name": "STUDIO A高雄三多",
    "sender_name": "晶實科技股份有限公司",
    "created_at": "2026/05/14",
    "notes": "044260514001",
    "status": "順利送達",
    "queried_at": "2026-05-21T01:10:23"
  },
  {
    "obt_number": "580033390051",
    "order_id": "",
    "recipient_name": "STUDIO A新西門",
    "sender_name": "晶實科技股份有限公司",
    "created_at": "2026/05/14",
    "notes": "",
    "status": "順利送達",
    "queried_at": "2026-05-21T01:10:24"
  },
  {
    "obt_number": "580033391763",
    "order_id": "035260514003",
    "recipient_name": "STUDIO A新竹遠百",
    "sender_name": "晶實科技股份有限公司",
    "created_at": "2026/05/14",
    "notes": "YQ4ZP/A",
    "status": "順利送達",
    "queried_at": "2026-05-21T01:10:24"
  },
  {
    "obt_number": "580033391886",
    "order_id": "門市調撥",
    "recipient_name": "STUDIO A岡山秀泰",
    "sender_name": "晶實科技股份有限公司",
    "created_at": "2026/05/14",
    "notes": "067260514002",
    "status": "順利送達",
    "queried_at": "2026-05-21T01:10:25"
  },
  {
    "obt_number": "909525101116",
    "order_id": "",
    "recipient_name": "STUDIO A士林維修中心",
    "sender_name": "晶實科技股份有限公司",
    "created_at": "2026/05/14",
    "notes": "",
    "status": "查無紀錄",
    "queried_at": "2026-05-21T01:20:02"
  },
  {
    "obt_number": "580033396884",
    "order_id": "027260515002",
    "recipient_name": "STUDIO A夢時代",
    "sender_name": "晶實科技股份有限公司",
    "created_at": "2026/05/15",
    "notes": "yp4",
    "status": "順利送達",
    "queried_at": "2026-05-21T01:10:22"
  },
  {
    "obt_number": "580033398954",
    "order_id": "門市調撥",
    "recipient_name": "STUDIO A花蓮",
    "sender_name": "晶實科技股份有限公司",
    "created_at": "2026/05/15",
    "notes": "055260515001",
    "status": "順利送達",
    "queried_at": "2026-05-21T01:10:23"
  },
  {
    "obt_number": "580033400645",
    "order_id": "",
    "recipient_name": "STUDIO A羅東",
    "sender_name": "晶實科技股份有限公司",
    "created_at": "2026/05/16",
    "notes": "",
    "status": "順利送達",
    "queried_at": "2026-05-21T01:10:22"
  },
  {
    "obt_number": "580033400840",
    "order_id": "",
    "recipient_name": "STUDIO A高雄三多",
    "sender_name": "晶實科技股份有限公司",
    "created_at": "2026/05/17",
    "notes": "",
    "status": "順利送達",
    "queried_at": "2026-05-21T01:10:21"
  },
  {
    "obt_number": "580033401444",
    "order_id": "",
    "recipient_name": "STUDIO A苗栗尚順",
    "sender_name": "晶實科技股份有限公司",
    "created_at": "2026/05/17",
    "notes": "",
    "status": "順利送達",
    "queried_at": "2026-05-21T01:10:21"
  },
  {
    "obt_number": "580033405590",
    "order_id": "",
    "recipient_name": "STUDIO A高雄三多",
    "sender_name": "晶實科技股份有限公司",
    "created_at": "2026/05/18",
    "notes": "044260518003",
    "status": "順利送達",
    "queried_at": "2026-05-21T01:10:20"
  },
  {
    "obt_number": "580033406486",
    "order_id": "門市調撥",
    "recipient_name": "STUDIO A新竹光復",
    "sender_name": "晶實科技股份有限公司",
    "created_at": "2026/05/18",
    "notes": "037260518002",
    "status": "順利送達",
    "queried_at": "2026-05-21T01:10:21"
  },
  {
    "obt_number": "580033417391",
    "order_id": "門市調撥",
    "recipient_name": "STUDIOA新莊宏匯",
    "sender_name": "晶實科技股份有限公司",
    "created_at": "2026/05/19",
    "notes": "064260519001",
    "status": "查無紀錄",
    "queried_at": "2026-05-21T01:20:02"
  },
  {
    "obt_number": "580033424622",
    "order_id": "",
    "recipient_name": "勁永國際股份有限公司",
    "sender_name": "晶實科技股份有限公司",
    "created_at": "2026/05/20",
    "notes": "DOA",
    "status": "查無紀錄",
    "queried_at": "2026-05-21T01:19:58"
  },
  {
    "obt_number": "580033424633",
    "order_id": "",
    "recipient_name": "薇恩企業社",
    "sender_name": "晶實科技股份有限公司",
    "created_at": "2026/05/20",
    "notes": "DOA",
    "status": "查無紀錄",
    "queried_at": "2026-05-21T01:19:58"
  },
  {
    "obt_number": "580033424644",
    "order_id": "",
    "recipient_name": "席德曼國際貿易有限公司",
    "sender_name": "晶實科技股份有限公司",
    "created_at": "2026/05/20",
    "notes": "",
    "status": "查無紀錄",
    "queried_at": "2026-05-21T01:19:59"
  },
  {
    "obt_number": "580033424655",
    "order_id": "",
    "recipient_name": "尚宏電子股份有限公司",
    "sender_name": "晶實科技股份有限公司",
    "created_at": "2026/05/20",
    "notes": "DOA",
    "status": "查無紀錄",
    "queried_at": "2026-05-21T01:19:59"
  },
  {
    "obt_number": "580033424734",
    "order_id": "",
    "recipient_name": "勁永國際股份有限公司",
    "sender_name": "晶實科技股份有限公司",
    "created_at": "2026/05/20",
    "notes": "",
    "status": "查無紀錄",
    "queried_at": "2026-05-21T01:20:00"
  },
  {
    "obt_number": "580033429383",
    "order_id": "DOA",
    "recipient_name": "麥克愛愛有限公司",
    "sender_name": "晶實科技股份有限公司",
    "created_at": "2026/05/20",
    "notes": "DOA",
    "status": "查無紀錄",
    "queried_at": "2026-05-21T01:20:00"
  },
  {
    "obt_number": "580033429552",
    "order_id": "MiddleT",
    "recipient_name": "STUDIO A台中精誠",
    "sender_name": "晶實科技股份有限公司",
    "created_at": "2026/05/20",
    "notes": "",
    "status": "查無紀錄",
    "queried_at": "2026-05-21T01:20:01"
  }
]